mkinit/__init__.py
mkinit/__main__.py
mkinit/_tokenize.py
mkinit/dynamic_mkinit.py
mkinit/formatting.py
mkinit/static_analysis.py
mkinit/static_mkinit.py
mkinit/top_level_ast.py
mkinit/util/__init__.py
mkinit/util/orderedset.py
mkinit/util/util_diff.py
mkinit/util/util_import.py
mkinit-1.1.0.dist-info/LICENCE
mkinit-1.1.0.dist-info/LICENSE
mkinit-1.1.0.dist-info/METADATA
mkinit-1.1.0.dist-info/WHEEL
mkinit-1.1.0.dist-info/entry_points.txt
mkinit-1.1.0.dist-info/top_level.txt
mkinit-1.1.0.dist-info/RECORD
