Metadata-Version: 2.1
Name: mkinit
Version: 1.1.0
Summary: Autogenerate __init__.py files
Home-page: https://github.com/Erotemic/mkinit
Author: Jon Crall
Author-email: erotemic@gmail.com
License: Apache 2
Platform: UNKNOWN
Classifier: Development Status :: 5 - Production/Stable
Classifier: Intended Audience :: Developers
Classifier: Topic :: Software Development :: Libraries :: Python Modules
Classifier: Topic :: Utilities
Classifier: License :: OSI Approved :: Apache Software License
Classifier: Programming Language :: Python :: 3.7
Classifier: Programming Language :: Python :: 3.8
Classifier: Programming Language :: Python :: 3.9
Classifier: Programming Language :: Python :: 3.10
Classifier: Programming Language :: Python :: 3.11
Classifier: Programming Language :: Python :: 3.12
Requires-Python: >=3.7
License-File: LICENCE
License-File: LICENSE
Requires-Dist: ubelt (>=1.3.4)
Provides-Extra: all
Requires-Dist: Pygments (>=2.2.0) ; extra == 'all'
Requires-Dist: packaging (>=21.3) ; extra == 'all'
Requires-Dist: ubelt (>=1.3.4) ; extra == 'all'
Requires-Dist: xdoctest (>=1.1.2) ; extra == 'all'
Provides-Extra: all-strict
Requires-Dist: Pygments (==2.2.0) ; extra == 'all-strict'
Requires-Dist: packaging (==21.3) ; extra == 'all-strict'
Requires-Dist: ubelt (==1.3.4) ; extra == 'all-strict'
Requires-Dist: xdoctest (==1.1.2) ; extra == 'all-strict'
Requires-Dist: colorama ; (platform_system == "Windows") and extra == 'all-strict'
Requires-Dist: coverage (==4.5) ; (python_version < "2.7" and python_version >= "2.6") and extra == 'all-strict'
Requires-Dist: pytest-cov (==2.8.1) ; (python_version < "2.8.0" and python_version >= "2.7.0") and extra == 'all-strict'
Requires-Dist: pytest (<=4.6.11,==4.6.0) ; (python_version < "2.8.0" and python_version >= "2.7.0") and extra == 'all-strict'
Requires-Dist: coverage (==5.3.1) ; (python_version < "3.10" and python_version >= "3.9") and extra == 'all-strict'
Requires-Dist: pytest (==4.6.0) ; (python_version < "3.10.0" and python_version >= "3.7.0") and extra == 'all-strict'
Requires-Dist: coverage (==5.3.1) ; (python_version < "3.4" and python_version >= "2.7") and extra == 'all-strict'
Requires-Dist: coverage (==4.3.4) ; (python_version < "3.5" and python_version >= "3.4") and extra == 'all-strict'
Requires-Dist: pytest-cov (==2.8.1) ; (python_version < "3.5.0" and python_version >= "3.4.0") and extra == 'all-strict'
Requires-Dist: pytest (<=4.6.11,==4.6.0) ; (python_version < "3.5.0" and python_version >= "3.4.0") and extra == 'all-strict'
Requires-Dist: coverage (==5.3.1) ; (python_version < "3.6" and python_version >= "3.5") and extra == 'all-strict'
Requires-Dist: pytest-cov (==2.9.0) ; (python_version < "3.6.0" and python_version >= "3.5.0") and extra == 'all-strict'
Requires-Dist: pytest (<=6.1.2,==4.6.0) ; (python_version < "3.6.0" and python_version >= "3.5.0") and extra == 'all-strict'
Requires-Dist: coverage (==6.1.1) ; (python_version < "3.7" and python_version >= "3.6") and extra == 'all-strict'
Requires-Dist: pytest (==4.6.0) ; (python_version < "3.7.0" and python_version >= "3.6.0") and extra == 'all-strict'
Requires-Dist: coverage (==6.1.1) ; (python_version < "3.8" and python_version >= "3.7") and extra == 'all-strict'
Requires-Dist: coverage (==6.1.1) ; (python_version < "3.9" and python_version >= "3.8") and extra == 'all-strict'
Requires-Dist: black ; (python_version > "3.5" and platform_python_implementation == "CPython") and extra == 'all-strict'
Requires-Dist: coverage (==6.1.1) ; (python_version >= "3.10") and extra == 'all-strict'
Requires-Dist: pytest (==6.2.5) ; (python_version >= "3.10.0") and extra == 'all-strict'
Requires-Dist: pytest-cov (==3.0.0) ; (python_version >= "3.6.0") and extra == 'all-strict'
Requires-Dist: lazy-loader (==0.3) ; (python_version >= "3.7.0") and extra == 'all-strict'
Requires-Dist: colorama ; (platform_system == "Windows") and extra == 'all'
Requires-Dist: coverage (>=4.5) ; (python_version < "2.7" and python_version >= "2.6") and extra == 'all'
Requires-Dist: pytest-cov (>=2.8.1) ; (python_version < "2.8.0" and python_version >= "2.7.0") and extra == 'all'
Requires-Dist: pytest (<=4.6.11,>=4.6.0) ; (python_version < "2.8.0" and python_version >= "2.7.0") and extra == 'all'
Requires-Dist: coverage (>=5.3.1) ; (python_version < "3.10" and python_version >= "3.9") and extra == 'all'
Requires-Dist: pytest (>=4.6.0) ; (python_version < "3.10.0" and python_version >= "3.7.0") and extra == 'all'
Requires-Dist: coverage (>=5.3.1) ; (python_version < "3.4" and python_version >= "2.7") and extra == 'all'
Requires-Dist: coverage (>=4.3.4) ; (python_version < "3.5" and python_version >= "3.4") and extra == 'all'
Requires-Dist: pytest-cov (>=2.8.1) ; (python_version < "3.5.0" and python_version >= "3.4.0") and extra == 'all'
Requires-Dist: pytest (<=4.6.11,>=4.6.0) ; (python_version < "3.5.0" and python_version >= "3.4.0") and extra == 'all'
Requires-Dist: coverage (>=5.3.1) ; (python_version < "3.6" and python_version >= "3.5") and extra == 'all'
Requires-Dist: pytest-cov (>=2.9.0) ; (python_version < "3.6.0" and python_version >= "3.5.0") and extra == 'all'
Requires-Dist: pytest (<=6.1.2,>=4.6.0) ; (python_version < "3.6.0" and python_version >= "3.5.0") and extra == 'all'
Requires-Dist: coverage (>=6.1.1) ; (python_version < "3.7" and python_version >= "3.6") and extra == 'all'
Requires-Dist: pytest (>=4.6.0) ; (python_version < "3.7.0" and python_version >= "3.6.0") and extra == 'all'
Requires-Dist: coverage (>=6.1.1) ; (python_version < "3.8" and python_version >= "3.7") and extra == 'all'
Requires-Dist: coverage (>=6.1.1) ; (python_version < "3.9" and python_version >= "3.8") and extra == 'all'
Requires-Dist: black ; (python_version > "3.5" and platform_python_implementation == "CPython") and extra == 'all'
Requires-Dist: coverage (>=6.1.1) ; (python_version >= "3.10") and extra == 'all'
Requires-Dist: pytest (>=6.2.5) ; (python_version >= "3.10.0") and extra == 'all'
Requires-Dist: pytest-cov (>=3.0.0) ; (python_version >= "3.6.0") and extra == 'all'
Requires-Dist: lazy-loader (>=0.3) ; (python_version >= "3.7.0") and extra == 'all'
Provides-Extra: docs
Requires-Dist: Pygments (>=2.9.0) ; extra == 'docs'
Requires-Dist: myst-parser (>=0.16.1) ; extra == 'docs'
Requires-Dist: sphinx-autoapi (>=1.8.4) ; extra == 'docs'
Requires-Dist: sphinx-autobuild (>=2021.3.14) ; extra == 'docs'
Requires-Dist: sphinx-reredirects (>=0.0.1) ; extra == 'docs'
Requires-Dist: sphinx (>=4.3.2) ; extra == 'docs'
Requires-Dist: sphinx-rtd-theme (>=1.0.0) ; extra == 'docs'
Requires-Dist: sphinxcontrib-napoleon (>=0.7) ; extra == 'docs'
Provides-Extra: docs-strict
Requires-Dist: Pygments (==2.9.0) ; extra == 'docs-strict'
Requires-Dist: myst-parser (==0.16.1) ; extra == 'docs-strict'
Requires-Dist: sphinx-autoapi (==1.8.4) ; extra == 'docs-strict'
Requires-Dist: sphinx-autobuild (==2021.3.14) ; extra == 'docs-strict'
Requires-Dist: sphinx-reredirects (==0.0.1) ; extra == 'docs-strict'
Requires-Dist: sphinx (==4.3.2) ; extra == 'docs-strict'
Requires-Dist: sphinx-rtd-theme (==1.0.0) ; extra == 'docs-strict'
Requires-Dist: sphinxcontrib-napoleon (==0.7) ; extra == 'docs-strict'
Provides-Extra: optional
Requires-Dist: Pygments (>=2.2.0) ; extra == 'optional'
Provides-Extra: optional-strict
Requires-Dist: Pygments (==2.2.0) ; extra == 'optional-strict'
Requires-Dist: colorama ; (platform_system == "Windows") and extra == 'optional-strict'
Requires-Dist: black ; (python_version > "3.5" and platform_python_implementation == "CPython") and extra == 'optional-strict'
Requires-Dist: colorama ; (platform_system == "Windows") and extra == 'optional'
Requires-Dist: black ; (python_version > "3.5" and platform_python_implementation == "CPython") and extra == 'optional'
Provides-Extra: runtime
Requires-Dist: ubelt (>=1.3.4) ; extra == 'runtime'
Provides-Extra: runtime-strict
Requires-Dist: ubelt (==1.3.4) ; extra == 'runtime-strict'
Provides-Extra: tests
Requires-Dist: packaging (>=21.3) ; extra == 'tests'
Requires-Dist: xdoctest (>=1.1.2) ; extra == 'tests'
Provides-Extra: tests-strict
Requires-Dist: packaging (==21.3) ; extra == 'tests-strict'
Requires-Dist: xdoctest (==1.1.2) ; extra == 'tests-strict'
Requires-Dist: coverage (==4.5) ; (python_version < "2.7" and python_version >= "2.6") and extra == 'tests-strict'
Requires-Dist: pytest-cov (==2.8.1) ; (python_version < "2.8.0" and python_version >= "2.7.0") and extra == 'tests-strict'
Requires-Dist: pytest (<=4.6.11,==4.6.0) ; (python_version < "2.8.0" and python_version >= "2.7.0") and extra == 'tests-strict'
Requires-Dist: coverage (==5.3.1) ; (python_version < "3.10" and python_version >= "3.9") and extra == 'tests-strict'
Requires-Dist: pytest (==4.6.0) ; (python_version < "3.10.0" and python_version >= "3.7.0") and extra == 'tests-strict'
Requires-Dist: coverage (==5.3.1) ; (python_version < "3.4" and python_version >= "2.7") and extra == 'tests-strict'
Requires-Dist: coverage (==4.3.4) ; (python_version < "3.5" and python_version >= "3.4") and extra == 'tests-strict'
Requires-Dist: pytest-cov (==2.8.1) ; (python_version < "3.5.0" and python_version >= "3.4.0") and extra == 'tests-strict'
Requires-Dist: pytest (<=4.6.11,==4.6.0) ; (python_version < "3.5.0" and python_version >= "3.4.0") and extra == 'tests-strict'
Requires-Dist: coverage (==5.3.1) ; (python_version < "3.6" and python_version >= "3.5") and extra == 'tests-strict'
Requires-Dist: pytest-cov (==2.9.0) ; (python_version < "3.6.0" and python_version >= "3.5.0") and extra == 'tests-strict'
Requires-Dist: pytest (<=6.1.2,==4.6.0) ; (python_version < "3.6.0" and python_version >= "3.5.0") and extra == 'tests-strict'
Requires-Dist: coverage (==6.1.1) ; (python_version < "3.7" and python_version >= "3.6") and extra == 'tests-strict'
Requires-Dist: pytest (==4.6.0) ; (python_version < "3.7.0" and python_version >= "3.6.0") and extra == 'tests-strict'
Requires-Dist: coverage (==6.1.1) ; (python_version < "3.8" and python_version >= "3.7") and extra == 'tests-strict'
Requires-Dist: coverage (==6.1.1) ; (python_version < "3.9" and python_version >= "3.8") and extra == 'tests-strict'
Requires-Dist: coverage (==6.1.1) ; (python_version >= "3.10") and extra == 'tests-strict'
Requires-Dist: pytest (==6.2.5) ; (python_version >= "3.10.0") and extra == 'tests-strict'
Requires-Dist: pytest-cov (==3.0.0) ; (python_version >= "3.6.0") and extra == 'tests-strict'
Requires-Dist: lazy-loader (==0.3) ; (python_version >= "3.7.0") and extra == 'tests-strict'
Requires-Dist: coverage (>=4.5) ; (python_version < "2.7" and python_version >= "2.6") and extra == 'tests'
Requires-Dist: pytest-cov (>=2.8.1) ; (python_version < "2.8.0" and python_version >= "2.7.0") and extra == 'tests'
Requires-Dist: pytest (<=4.6.11,>=4.6.0) ; (python_version < "2.8.0" and python_version >= "2.7.0") and extra == 'tests'
Requires-Dist: coverage (>=5.3.1) ; (python_version < "3.10" and python_version >= "3.9") and extra == 'tests'
Requires-Dist: pytest (>=4.6.0) ; (python_version < "3.10.0" and python_version >= "3.7.0") and extra == 'tests'
Requires-Dist: coverage (>=5.3.1) ; (python_version < "3.4" and python_version >= "2.7") and extra == 'tests'
Requires-Dist: coverage (>=4.3.4) ; (python_version < "3.5" and python_version >= "3.4") and extra == 'tests'
Requires-Dist: pytest-cov (>=2.8.1) ; (python_version < "3.5.0" and python_version >= "3.4.0") and extra == 'tests'
Requires-Dist: pytest (<=4.6.11,>=4.6.0) ; (python_version < "3.5.0" and python_version >= "3.4.0") and extra == 'tests'
Requires-Dist: coverage (>=5.3.1) ; (python_version < "3.6" and python_version >= "3.5") and extra == 'tests'
Requires-Dist: pytest-cov (>=2.9.0) ; (python_version < "3.6.0" and python_version >= "3.5.0") and extra == 'tests'
Requires-Dist: pytest (<=6.1.2,>=4.6.0) ; (python_version < "3.6.0" and python_version >= "3.5.0") and extra == 'tests'
Requires-Dist: coverage (>=6.1.1) ; (python_version < "3.7" and python_version >= "3.6") and extra == 'tests'
Requires-Dist: pytest (>=4.6.0) ; (python_version < "3.7.0" and python_version >= "3.6.0") and extra == 'tests'
Requires-Dist: coverage (>=6.1.1) ; (python_version < "3.8" and python_version >= "3.7") and extra == 'tests'
Requires-Dist: coverage (>=6.1.1) ; (python_version < "3.9" and python_version >= "3.8") and extra == 'tests'
Requires-Dist: coverage (>=6.1.1) ; (python_version >= "3.10") and extra == 'tests'
Requires-Dist: pytest (>=6.2.5) ; (python_version >= "3.10.0") and extra == 'tests'
Requires-Dist: pytest-cov (>=3.0.0) ; (python_version >= "3.6.0") and extra == 'tests'
Requires-Dist: lazy-loader (>=0.3) ; (python_version >= "3.7.0") and extra == 'tests'
